MANIFEST.in
readme.rst
setup.py
src/sirep/__init__.py
src/sirep/admin.py
src/sirep/base.py
src/sirep/conf.py
src/sirep/constants.py
src/sirep/defaults.py
src/sirep/forms.py
src/sirep/models.py
src/sirep/reports.py
src/sirep/urls.py
src/sirep/views.py
src/sirep/writers.py
src/sirep.egg-info/PKG-INFO
src/sirep.egg-info/SOURCES.txt
src/sirep.egg-info/dependency_links.txt
src/sirep.egg-info/requires.txt
src/sirep.egg-info/top_level.txt
src/sirep/static/admin/css/sirep.css
src/sirep/templates/sirep/list.html
src/sirep/templates/sirep/view.html
src/sirep/templatetags/__init__.py
src/sirep/templatetags/sirep_tags.py