Metadata-Version: 1.1
Name: sirep
Version: 0.4
Summary: Simple reporting for Django admin.
Home-page: https://bitbucket.org/barseghyanartur/sirep
Author: Artur Barseghyan
Author-email: artur.barseghyan@gmail.com
License: GPL 2.0/LGPL 2.1
Keywords: reporting,django,admin,app,python
Platform: UNKNOWN
Classifier: Framework :: Django
Classifier: Programming Language :: Python
Classifier: Environment :: Web Environment
Classifier: Intended Audience :: Developers
Classifier: Operating System :: OS Independent
